<?xml version="1.0" encoding="UTF-8"?>
<beans xmlns="http://www.springframework.org/schema/beans"
       xmlns:xsi="http://www.w3.org/2001/XMLSchema-instance"
       xsi:schemaLocation="http://www.springframework.org/schema/beans http://www.springframework.org/schema/beans/spring-beans.xsd">

    <bean id="contactMessageBean" class="com.zygstore.business.ContactMessageBean">
        <property name="contactMessageService" ref="contactMessageService" />
    </bean>

    <bean id="contactMessageDTO" class="com.zygstore.dto.ContactMessageDTO">
        <constructor-arg name="firstname" value=""/>
        <constructor-arg name="secondname" value=""/>
        <constructor-arg name="email" value=""/>
        <constructor-arg name="phone" value=""/>
        <constructor-arg name="issueType" value=""/>
        <constructor-arg name="messageText" value=""/>
        <constructor-arg name="clientAlready" value=""/>
    </bean>

    <bean id="contactMessageService" class="com.zygstore.service.ContactMessageService">
        <constructor-arg name="sendEmailService" ref="sendEmailService" />
    </bean>

    <bean id="sendEmailService" class="com.zygstore.service.SendEmailService">
        <constructor-arg name="emailConfig" ref="emailConfig"/>
    </bean>

    <bean id="emailConfig" class="com.zygstore.config.EmailConfig">
        <constructor-arg name="hostName" value="relayinternal.nykreditnet.net"/>
        <constructor-arg name="username" value="y08l@nykredit.dk"/>
        <constructor-arg name="password" value=""/>
        <constructor-arg name="port" value="25"/>
        <constructor-arg name="auth" value="true"/>
    </bean>

</beans>